<Transaction 
    xmlns="http://www.opengis.net/wfs" service="WFS" version="1.1.0" xsi:schemaLocation="http://www.opengis.net/wfs http://schemas.opengis.net/wfs/1.1.0/wfs.xsd" 
    xmlns:xsi="http://www.w3.org/2001/XMLSchema-instance">
    <Insert>
        <tmc:tasiemki 
            xmlns:tmc="http://ksg.eti.pg.gda.pl/geoserver/tmc/wfs">
            <tmc:geometry>
                <LineString xmlns="http://www.opengis.net/gml">
                    <posList>2061923.748766359 7240473.605692343 2058789.8306066666 7238753.772555926 2063643.5819027752 7238065.83930136 2063758.2374452031 7239823.890951918</posList>
                </LineString>
            </tmc:geometry>
        </tmc:tasiemki>
    </Insert>
</Transaction>